ez_kaggle/__init__.py
ez_kaggle/_modidx.py
ez_kaggle/dataset.py
ez_kaggle/kernel.py
ez_kaggle/setup.py
ez_kaggle-0.0.1.dist-info/LICENSE
ez_kaggle-0.0.1.dist-info/METADATA
ez_kaggle-0.0.1.dist-info/WHEEL
ez_kaggle-0.0.1.dist-info/entry_points.txt
ez_kaggle-0.0.1.dist-info/top_level.txt
ez_kaggle-0.0.1.dist-info/RECORD
