Metadata-Version: 2.1
Name: ez-kaggle
Version: 0.0.1
Summary: API to make interacting with kaggle faster for common operations
Home-page: https://github.com/Isaac-Flath/ez-kaggle
Author: Isaac Flath
Author-email: Isaac.flath@gmail.com
License: Apache Software License 2.0
Keywords: nbdev jupyter notebook python kaggle
Platform: UNKNOWN
Classifier: Development Status :: 4 - Beta
Classifier: Intended Audience :: Developers
Classifier: Natural Language :: English
Classifier: Programming Language :: Python :: 3.7
Classifier: Programming Language :: Python :: 3.8
Classifier: Programming Language :: Python :: 3.9
Classifier: Programming Language :: Python :: 3.10
Classifier: License :: OSI Approved :: Apache Software License
Requires-Python: >=3.7
License-File: LICENSE
Requires-Dist: fastcore
Requires-Dist: nbdev
Requires-Dist: execnb
Requires-Dist: kaggle
Provides-Extra: dev
Requires-Dist: fastai ; extra == 'dev'
Requires-Dist: pandas ; extra == 'dev'
